JMESpand-0.1.1.dist-info/DESCRIPTION.rst
JMESpand-0.1.1.dist-info/METADATA
JMESpand-0.1.1.dist-info/RECORD
JMESpand-0.1.1.dist-info/WHEEL
JMESpand-0.1.1.dist-info/metadata.json
JMESpand-0.1.1.dist-info/top_level.txt
JMESpand-0.1.1.dist-info/zip-safe
jmespand/__init__.py
jmespand/_formatter.py
jmespand/_root.py
