Metadata-Version: 2.0
Name: JMESpand
Version: 0.1.1
Summary: Configuration template expansion system using JMESpath
Home-page: https://github.com/rickardp/jmespand
Author: Rickard Lyrenius
Author-email: rickard@evolviq.com
License: UNKNOWN
Platform: UNKNOWN
Classifier: License :: OSI Approved :: Apache Software License
Classifier: Topic :: Software Development :: Libraries :: Python Modules
Classifier: Programming Language :: Python
Classifier: Programming Language :: Python :: 2
Classifier: Programming Language :: Python :: 2.7
Classifier: Programming Language :: Python :: 3
Classifier: Programming Language :: Python :: 3.4
Classifier: Programming Language :: Python :: 3.6
Classifier: Programming Language :: Python :: 3.7
Classifier: Programming Language :: Python :: Implementation :: CPython
Classifier: Programming Language :: Python :: Implementation :: PyPy
Classifier: Intended Audience :: Developers
Requires-Dist: jmespath (<1.0.0,>=0.9.3)
